bkmrks/__init__.py
bkmrks/__main__.py
bkmrks/bkmrks.py
bkmrks/files.py
bkmrks/folders.py
bkmrks/icons.py
bkmrks/md.py
bkmrks/presenter.py
bkmrks/urls.py
bkmrks/templates/index.css
bkmrks/templates/index.html
bkmrks/templates/index.js
bkmrks/templates/menu_item.html
bkmrks-0.5.1.dist-info/METADATA
bkmrks-0.5.1.dist-info/WHEEL
bkmrks-0.5.1.dist-info/entry_points.txt
bkmrks-0.5.1.dist-info/top_level.txt
bkmrks-0.5.1.dist-info/RECORD
