Metadata-Version: 2.4
Name: bkmrks
Version: 0.5.1
Summary: 🔖 Bkmrks helps you to manage your bookmarks.
Author-email: Cesar Cardoso <hello@cesarcardoso.cc>
License-Expression: MIT
Project-URL: Repository, https://github.com/bouli/bkmrks
Project-URL: Changelog, https://github.com/bouli/bkmrks/releases/latest
Requires-Python: >=3.11
Requires-Dist: bs4>=0.0.2
Requires-Dist: dotenv>=0.9.9
Requires-Dist: markdown>=3.10.1
Requires-Dist: pyyaml>=6.0.3
Requires-Dist: requests>=2.32.5
